esp_idf_panic_decoder/__init__.py
esp_idf_panic_decoder/__main__.py
esp_idf_panic_decoder/gdb_panic_server.py
esp_idf_panic_decoder/output_helpers.py
esp_idf_panic_decoder/panic_output_decoder.py
esp_idf_panic_decoder/pc_address_decoder.py
esp_idf_panic_decoder/pc_address_matcher.py
esp_idf_panic_decoder-1.4.1.dist-info/licenses/LICENSE
esp_idf_panic_decoder-1.4.1.dist-info/METADATA
esp_idf_panic_decoder-1.4.1.dist-info/WHEEL
esp_idf_panic_decoder-1.4.1.dist-info/top_level.txt
esp_idf_panic_decoder-1.4.1.dist-info/RECORD
