Metadata-Version: 2.4
Name: esp_idf_panic_decoder
Version: 1.4.1
Summary: ESP-IDF panic decoder
Author: Espressif Systems
License:                                  Apache License
Project-URL: Homepage, https://github.com/espressif/esp-idf-panic-decoder
Keywords: python,espressif,gdb,panic-decoder
Classifier: Development Status :: 5 - Production/Stable
Classifier: Intended Audience :: Developers
Classifier: Natural Language :: English
Classifier: Environment :: Console
Classifier: Topic :: Software Development :: Embedded Systems
Classifier: License :: OSI Approved :: Apache Software License
Classifier: Programming Language :: Python :: 3.7
Classifier: Programming Language :: Python :: 3.8
Classifier: Programming Language :: Python :: 3.9
Classifier: Programming Language :: Python :: 3.10
Classifier: Programming Language :: Python :: 3.11
Classifier: Programming Language :: Python :: 3.12
Classifier: Programming Language :: Python :: 3.13
Classifier: Operating System :: POSIX
Classifier: Operating System :: Microsoft :: Windows
Classifier: Operating System :: MacOS :: MacOS X
Requires-Python: >=3.7
License-File: LICENSE
Requires-Dist: pyelftools
Provides-Extra: dev
Requires-Dist: pre-commit; extra == "dev"
Requires-Dist: czespressif; extra == "dev"
Dynamic: license-file
